[
  {
    "imageSrc": "https://images.unsplash.com/photo-1460925895917-afdab827c52f?w=800&q=80",
    "title": "CIDA (UNRELEASED, PLACEHOLDER)",
    "description": "Data aggregation pipeline that analyzes and generates reports on HOA's.",
    "date": "Dec 12, 2024",
    "tags": ["Python", "TypeScript", "PostgreSQL", "FastAPI"]
  },
  {
    "imageSrc": "https://images.unsplash.com/photo-1551288049-bebda4e38f71?w=800&q=80",
    "title": "HeadCount (UNRELEASED, PLACEHOLDER)",
    "description": "Generate optimized schedules based on availabilities and staffing requirements.",
    "date": "Nov 19, 2023",
    "tags": ["Python", "TypeScript", "MySQL", "Flask"]
  },
  {
    "imageSrc": "https://images.unsplash.com/photo-1504384308090-c894fdcc538d?w=800&q=80",
    "title": "RealDoc.app",
    "description": "Web app built for real estate agencies automating CE certification generation.",
    "date": "May 29, 2022",
    "tags": ["Python", "TypeScript", "MySQL", "Flask"],
    "githubUrl": "https://github.com",
    "liveDemoUrl": "https://realdoc.app",
    "titleClassName": "hover:text-brand-primary transition-colors",
    "descriptionClassName": "whitespace-normal"
  },
  {
    "imageSrc": "https://images.unsplash.com/photo-1552664730-d307ca884978?w=800&q=80",
    "title": "Pipeline Monitor (PLACEHOLDER)",
    "description": "Observability dashboard for distributed data workflows.",
    "date": "Jan 09, 2025",
    "tags": ["TypeScript", "React", "PostgreSQL", "Redis"]
  },
  {
    "imageSrc": "https://images.unsplash.com/photo-1454165804606-c3d57bc86b40?w=800&q=80",
    "title": "Ops Board (PLACEHOLDER)",
    "description": "Operational planning and handoff system for internal teams.",
    "date": "Feb 03, 2025",
    "tags": ["Next.js", "Node.js", "OpenAPI", "Docker"]
  },
  {
    "imageSrc": "https://images.unsplash.com/photo-1518773553398-650c184e0bb3?w=800&q=80",
    "title": "Doc Automation (PLACEHOLDER)",
    "description": "Template-driven document generation and workflow automation.",
    "date": "Mar 15, 2025",
    "tags": ["Python", "FastAPI", "RabbitMQ", "MySQL"]
  },
  {
    "imageSrc": "https://images.unsplash.com/photo-1461749280684-dccba630e2f6?w=800&q=80",
    "title": "Hiring Hub (PLACEHOLDER)",
    "description": "Candidate tracking and interview score aggregation platform.",
    "date": "Apr 11, 2025",
    "tags": ["TypeScript", "React", "MongoDB", "Express"]
  },
  {
    "imageSrc": "https://images.unsplash.com/photo-1551434678-e076c223a692?w=800&q=80",
    "title": "Load Planner (PLACEHOLDER)",
    "description": "Capacity forecasting and utilization planning tool.",
    "date": "May 04, 2025",
    "tags": ["Python", "SQL", "Flask", "Redis"]
  },
  {
    "imageSrc": "https://images.unsplash.com/photo-1526374965328-7f61d4dc18c5?w=800&q=80",
    "title": "Audit Trail (PLACEHOLDER)",
    "description": "Immutable audit history for regulated data operations.",
    "date": "Jun 27, 2025",
    "tags": ["Node.js", "PostgreSQL", "Docker", "AWS"]
  },
  {
    "imageSrc": "https://images.unsplash.com/photo-1515879218367-8466d910aaa4?w=800&q=80",
    "title": "Queue Insights (PLACEHOLDER)",
    "description": "Real-time queue analytics and SLA alerting service.",
    "date": "Jul 12, 2025",
    "tags": ["TypeScript", "RabbitMQ", "Redis", "Grafana"]
  },
  {
    "imageSrc": "https://images.unsplash.com/photo-1460925895917-afdab827c52f?w=800&q=80",
    "title": "Report Studio (PLACEHOLDER)",
    "description": "Self-service reporting builder with export automation.",
    "date": "Aug 01, 2025",
    "tags": ["React", "FastAPI", "PostgreSQL", "OpenAPI"]
  },
  {
    "imageSrc": "https://images.unsplash.com/photo-1551288049-bebda4e38f71?w=800&q=80",
    "title": "Infra Pulse (PLACEHOLDER)",
    "description": "Infrastructure health scoring and anomaly detection.",
    "date": "Aug 28, 2025",
    "tags": ["Python", "AWS", "Docker", "Prometheus"]
  },
  {
    "imageSrc": "https://images.unsplash.com/photo-1504384308090-c894fdcc538d?w=800&q=80",
    "title": "Schedule Sync (PLACEHOLDER)",
    "description": "Cross-team scheduling optimizer with conflict resolution.",
    "date": "Sep 14, 2025",
    "tags": ["TypeScript", "Node.js", "MySQL", "Redis"]
  },
  {
    "imageSrc": "https://images.unsplash.com/photo-1552664730-d307ca884978?w=800&q=80",
    "title": "Client Portal (PLACEHOLDER)",
    "description": "Secure project portal for client communication and updates.",
    "date": "Oct 06, 2025",
    "tags": ["Next.js", "PostgreSQL", "CORS", "OpenAPI"]
  },
  {
    "imageSrc": "https://images.unsplash.com/photo-1454165804606-c3d57bc86b40?w=800&q=80",
    "title": "Workflow Maps (PLACEHOLDER)",
    "description": "Visual process mapping and automation trigger designer.",
    "date": "Nov 21, 2025",
    "tags": ["React", "FastAPI", "MongoDB", "RabbitMQ"]
  }
]
